ssr_rts_api/Client.py
ssr_rts_api/__init__.py
ssr_rts_api-0.0.10.dist-info/LICENSE
ssr_rts_api-0.0.10.dist-info/METADATA
ssr_rts_api-0.0.10.dist-info/WHEEL
ssr_rts_api-0.0.10.dist-info/top_level.txt
ssr_rts_api-0.0.10.dist-info/RECORD
