Metadata-Version: 2.1
Name: ssr-rts-api
Version: 0.0.10
Summary: Connect with ease to the public rts/ssr public API.
Home-page: https://github.com/rerouj/ssr_rts_api
Author: Renato Diaz (rouj)
Author-email: renatojour@gmail.com
License: UNKNOWN
Keywords: ssr,rts,tsr,ssr rts api
Platform: UNKNOWN
Classifier: Programming Language :: Python :: 3
Requires-Python: >=3.6
